{"id": "cdb75001-12a4-43c1-9efa-0319f2aa902c", "name": "Farmers Insurance Open", "event_type": "stroke", "purse": 7500000.0, "winning_share": 1350000.0, "currency": "USD", "points": 500, "start_date": "2020-01-23", "end_date": "2020-01-26", "course_timezone": "America/Los_Angeles", "status": "closed", "cut_round": 2, "seasons": [{"id": "83eb0a3a-dd69-40d3-a9ba-f49e398fdb61", "year": 2020, "tour": {"id": "b52068af-28e4-4e91-bdbb-037591b0ff84", "alias": "pga", "name": "PGA Tour"}}], "coverage": "full", "venue": {"id": "1c12ad8a-336e-40a6-90bb-50b86321c0f9", "name": "Torrey Pines", "city": "La Jolla", "state": "CA", "zipcode": "92037", "country": "USA", "courses": [{"id": "5401065a-a685-4aeb-a9d7-602d9a3690d0", "name": "TORREY PINES - SOUTH", "yardage": 7765, "par": 72, "holes": [{"number": 1, "par": 4, "yardage": 451}, {"number": 2, "par": 4, "yardage": 389}, {"number": 3, "par": 3, "yardage": 201}, {"number": 4, "par": 4, "yardage": 490}, {"number": 5, "par": 4, "yardage": 454}, {"number": 6, "par": 5, "yardage": 564}, {"number": 7, "par": 4, "yardage": 462}, {"number": 8, "par": 3, "yardage": 177}, {"number": 9, "par": 5, "yardage": 615}, {"number": 10, "par": 4, "yardage": 454}, {"number": 11, "par": 3, "yardage": 225}, {"number": 12, "par": 4, "yardage": 505}, {"number": 13, "par": 5, "yardage": 621}, {"number": 14, "par": 4, "yardage": 437}, {"number": 15, "par": 4, "yardage": 480}, {"number": 16, "par": 3, "yardage": 227}, {"number": 17, "par": 4, "yardage": 443}, {"number": 18, "par": 5, "yardage": 570}]}, {"id": "9034c516-80ec-4670-9345-ed8a6b29904b", "name": "TORREY PINES - NORTH", "yardage": 7258, "par": 72, "holes": [{"number": 1, "par": 4, "yardage": 421}, {"number": 2, "par": 4, "yardage": 495}, {"number": 3, "par": 3, "yardage": 241}, {"number": 4, "par": 4, "yardage": 479}, {"number": 5, "par": 5, "yardage": 525}, {"number": 6, "par": 4, "yardage": 416}, {"number": 7, "par": 4, "yardage": 322}, {"number": 8, "par": 3, "yardage": 214}, {"number": 9, "par": 5, "yardage": 556}, {"number": 10, "par": 5, "yardage": 536}, {"number": 11, "par": 4, "yardage": 339}, {"number": 12, "par": 3, "yardage": 203}, {"number": 13, "par": 4, "yardage": 459}, {"number": 14, "par": 4, "yardage": 451}, {"number": 15, "par": 3, "yardage": 202}, {"number": 16, "par": 4, "yardage": 393}, {"number": 17, "par": 5, "yardage": 520}, {"number": 18, "par": 4, "yardage": 486}]}]}, "rounds": [{"id": "e5c7e17b-92e5-4c94-a5ba-ddf7a6d493cd", "number": 1, "status": "closed", "weather": {"temp": 67, "condition": "Sunny", "wind": {"speed": 8, "direction": "NW"}}}, {"id": "524eafd4-f9cd-440c-ac8c-c1a9c4718997", "number": 2, "status": "closed", "weather": {"temp": 65, "condition": "Sunny", "wind": {"speed": 7, "direction": "WSW"}}}, {"id": "b6129c58-cada-4029-9450-4f0794767285", "number": 3, "status": "closed", "weather": {"temp": 63, "condition": "Haze", "wind": {"speed": 6, "direction": "WSW"}}}, {"id": "69d65a25-f9f3-472c-93ae-bfa9848c5143", "number": 4, "status": "closed", "weather": {"temp": 60, "condition": "Partly cloudy", "wind": {"speed": 0, "direction": "N"}}}], "field": [{"id": "5a9ea77c-7323-4f26-86b5-f6adc3b7e00a", "first_name": "Byeong Hun", "last_name": "An", "country": "SOUTH KOREA", "abbr_name": "B.An"}, {"id": "68ccac6a-048d-4ed1-99ce-5a31a12b4c8d", "first_name": "Mark", "last_name": "Anderson", "country": "UNITED STATES", "abbr_name": "M.Anderson"}, {"id": "f85fbf33-5afb-4749-a120-be2cdc2c6e2e", "first_name": "Aaron", "last_name": "Baddeley", "country": "AUSTRALIA", "abbr_name": "A.Baddeley"}, {"id": "2f0d6183-3427-4655-910d-8791ed2a79b6", "first_name": "Chris", "last_name": "Baker", "country": "UNITED STATES", "abbr_name": "C.Baker"}, {"id": "0ef8df39-16ef-4e38-aca7-d000394ba995", "first_name": "Alex", "last_name": "Beach", "country": "UNITED STATES", "abbr_name": "A.Beach"}, {"id": "0d64124c-6361-4106-b2ee-ca23df0251cd", "first_name": "Jacob", "last_name": "Bergeron", "country": "UNITED STATES", "abbr_name": "J.Bergeron"}, {"id": "abf5adcb-8130-4fd1-bc3b-e7acc3d71152", "first_name": "Lucas", "last_name": "Bjerregaard", "country": "DENMARK", "abbr_name": "L.Bjerregaard"}, {"id": "8b1fc211-813d-4a1b-b896-0107cfb84119", "first_name": "Zac", "last_name": "Blair", "country": "UNITED STATES", "abbr_name": "Z.Blair"}, {"id": "5b42c5fc-6f2a-4702-9aac-9f4bb4243aaf", "first_name": "Michael", "last_name": "Block", "country": "UNITED STATES", "abbr_name": "M.Block"}, {"id": "f1d5434f-0b3a-490c-bf11-639b6f676ecb", "first_name": "Dominic", "last_name": "Bozzelli", "country": "UNITED STATES", "abbr_name": "D.Bozzelli"}, {"id": "0b5d3fd6-e3ec-4efd-8743-60db44c87425", "first_name": "Keegan", "last_name": "Bradley", "country": "UNITED STATES", "abbr_name": "K.Bradley"}, {"id": "848d977f-f10f-4d59-ab08-6665e7ee4b2f", "first_name": "Joseph", "last_name": "Bramlett", "country": "UNITED STATES", "abbr_name": "J.Bramlett"}, {"id": "84e36539-504b-4566-9b77-4f7ae4a28bce", "first_name": "Ryan", "last_name": "Brehm", "country": "UNITED STATES", "abbr_name": "R.Brehm"}, {"id": "36fef62c-2138-4c5d-9519-f6d25581d9d0", "first_name": "Scott", "last_name": "Brown", "country": "UNITED STATES", "abbr_name": "S.Brown"}, {"id": "ed67db92-af39-4ea1-9b67-47d94b63bc19", "first_name": "Bronson", "last_name": "Burgoon", "country": "UNITED STATES", "abbr_name": "B.Burgoon"}, {"id": "f572509d-7c6d-48b9-9c65-a20f6d2d492b", "first_name": "Sam", "last_name": "Burns", "country": "UNITED STATES", "abbr_name": "S.Burns"}, {"id": "e4e087c0-088f-4a1f-99e2-d677a6ae0ffc", "first_name": "Sebastian", "last_name": "Cappelen", "country": "DENMARK", "abbr_name": "S.Cappelen"}, {"id": "6383ba29-158b-46fe-b44a-a5ff6a2796bb", "first_name": "Bud", "last_name": "Cauley", "country": "UNITED STATES", "abbr_name": "B.Cauley"}, {"id": "72b7246a-6391-4024-8d0f-35fa1c459664", "first_name": "Cameron", "last_name": "Champ", "country": "UNITED STATES", "abbr_name": "C.Champ"}, {"id": "e6983206-aaf0-4117-a5b8-2d7770044182", "first_name": "K.J.", "last_name": "Choi", "country": "SOUTH KOREA", "abbr_name": "K.Choi"}, {"id": "d2277a8b-80d5-48a8-9f8d-3b39cf2cf8e0", "first_name": "Stewart", "last_name": "Cink", "country": "UNITED STATES", "abbr_name": "S.Cink"}, {"id": "0f2eb1c3-7278-4b5e-af2e-fd67644834b5", "first_name": "Wyndham", "last_name": "Clark", "country": "UNITED STATES", "abbr_name": "W.Clark"}, {"id": "1f189584-ff86-42da-9743-40397cb9d5ff", "first_name": "Austin", "last_name": "Cook", "country": "UNITED STATES", "abbr_name": "A.Cook"}, {"id": "b63b6650-7b73-4c72-9c86-96d26d12c25e", "first_name": "Vince", "last_name": "Covello", "country": "UNITED STATES", "abbr_name": "V.Covello"}, {"id": "e8860c1b-85bf-4997-8f60-cf8681935219", "first_name": "Joel", "last_name": "Dahmen", "country": "UNITED STATES", "abbr_name": "J.Dahmen"}, {"id": "f2bc6b83-fab1-4567-8bcf-9287d1940f2d", "first_name": "Cameron", "last_name": "Davis", "country": "AUSTRALIA", "abbr_name": "C.Davis"}, {"id": "97cd8ce8-beb2-484e-9081-ccba9baa0607", "first_name": "Jason", "last_name": "Day", "country": "AUSTRALIA", "abbr_name": "J.Day"}, {"id": "4dc6e9c7-dd5b-4cf2-a7fe-b9c94c7a9110", "first_name": "Jason", "last_name": "Dufner", "country": "UNITED STATES", "abbr_name": "J.Dufner"}, {"id": "7e11058b-ce7b-4efa-8963-2e48c683ff5b", "first_name": "Harris", "last_name": "English", "country": "UNITED STATES", "abbr_name": "H.English"}, {"id": "f33d746b-8e14-4325-a4e1-81d6f983b163", "first_name": "Tony", "last_name": "Finau", "country": "UNITED STATES", "abbr_name": "T.Finau"}, {"id": "5735703a-32d9-4a6c-8b24-6596f300bc44", "first_name": "Rickie", "last_name": "Fowler", "country": "UNITED STATES", "abbr_name": "R.Fowler"}, {"id": "1c228994-a417-4452-896c-e77cdbe9af6b", "first_name": "Dylan", "last_name": "Frittelli", "country": "SOUTH AFRICA", "abbr_name": "D.Frittelli"}, {"id": "bf4cdcde-0887-4396-9aac-3cd1cdff4fcf", "first_name": "Michael", "last_name": "Gellerman", "country": "UNITED STATES", "abbr_name": "M.Gellerman"}, {"id": "fa4b1348-de92-49e6-9379-b96b936055fe", "first_name": "Doug", "last_name": "Ghim", "country": "UNITED STATES", "abbr_name": "D.Ghim"}, {"id": "b363c835-649f-4ad8-b961-f27aecfa8462", "first_name": "Rhein", "last_name": "Gibson", "country": "AUSTRALIA", "abbr_name": "R.Gibson"}, {"id": "c76bb673-b234-4f2c-9dca-7de2871a87a5", "first_name": "Michael", "last_name": "Gligic", "country": "CANADA", "abbr_name": "M.Gligic"}, {"id": "88c2edb1-7551-4920-91ad-71c971e51e8c", "first_name": "Lucas", "last_name": "Glover", "country": "UNITED STATES", "abbr_name": "L.Glover"}, {"id": "17d9be3d-a0a4-4a8c-a2ac-d127050f42c0", "first_name": "Fabian", "last_name": "Gomez", "country": "ARGENTINA", "abbr_name": "F.Gomez"}, {"id": "c2e2cf74-3fc1-4c18-8bf5-8693ad9e0943", "first_name": "Talor", "last_name": "Gooch", "country": "UNITED STATES", "abbr_name": "T.Gooch"}, {"id": "61998611-8d8f-424c-b3df-2e1fb49162f7", "first_name": "Will", "last_name": "Gordon", "country": "UNITED STATES", "abbr_name": "W.Gordon"}, {"id": "0cfa22b7-e601-49f6-b85b-3dfd54cf652e", "first_name": "Lanto", "last_name": "Griffin", "country": "UNITED STATES", "abbr_name": "L.Griffin"}, {"id": "f1fb4562-ffe8-4539-927b-0ffd13e9533f", "first_name": "Emiliano", "last_name": "Grillo", "country": "ARGENTINA", "abbr_name": "E.Grillo"}, {"id": "a9eb0570-9edd-4de7-8886-f95430d47550", "first_name": "Bill", "last_name": "Haas", "country": "UNITED STATES", "abbr_name": "B.Haas"}, {"id": "da0ff4ff-57a6-47eb-9b3e-3d9a544162e4", "first_name": "Chesson", "last_name": "Hadley", "country": "UNITED STATES", "abbr_name": "C.Hadley"}, {"id": "3faf4d41-ee03-4dbc-9108-d2ca2dad1ba0", "first_name": "Brandon", "last_name": "Hagy", "country": "UNITED STATES", "abbr_name": "B.Hagy"}, {"id": "be5be8d0-b561-4d0e-ac4a-90275f2f979f", "first_name": "Harry", "last_name": "Hall", "country": "ENGLAND", "abbr_name": "H.Hall"}, {"id": "619dfef2-c385-408a-ab62-c89c9b3a8c50", "first_name": "Scott", "last_name": "Harrington", "country": "UNITED STATES", "abbr_name": "S.Harrington"}, {"id": "103a91f0-ea5a-40ad-b0f3-08d67f82aa64", "first_name": "Jim", "last_name": "Herman", "country": "UNITED STATES", "abbr_name": "J.Herman"}, {"id": "73d2d814-c689-497b-a39d-5dcd9b5dc2fc", "first_name": "Kramer", "last_name": "Hickok", "country": "UNITED STATES", "abbr_name": "K.Hickok"}, {"id": "2bb9e2cd-4dbb-4478-a425-218d71a6de4e", "first_name": "Harry", "last_name": "Higgs", "country": "UNITED STATES", "abbr_name": "H.Higgs"}, {"id": "7a0097e4-6885-4798-a69d-16dcf56bbd34", "first_name": "Bo", "last_name": "Hoag", "country": "UNITED STATES", "abbr_name": "B.Hoag"}, {"id": "25366155-7268-4630-baf7-7a27d5e18385", "first_name": "Charley", "last_name": "Hoffman", "country": "UNITED STATES", "abbr_name": "C.Hoffman"}, {"id": "dae7d61f-bde2-4182-9e99-06b48689f004", "first_name": "Tom", "last_name": "Hoge", "country": "UNITED STATES", "abbr_name": "T.Hoge"}, {"id": "1ec2172c-ed08-493c-b2bc-0df2511b2a8a", "first_name": "J.B.", "last_name": "Holmes", "country": "UNITED STATES", "abbr_name": "J.Holmes"}, {"id": "8e3fb27f-d585-4b9e-9c0e-284a654969f5", "first_name": "Max", "last_name": "Homa", "country": "UNITED STATES", "abbr_name": "M.Homa"}, {"id": "f04f89c3-3f8f-4009-bc49-0de2a634ead3", "first_name": "Billy", "last_name": "Horschel", "country": "UNITED STATES", "abbr_name": "B.Horschel"}, {"id": "7060c098-0919-4fbb-9c12-c396378fd6e5", "first_name": "Beau", "last_name": "Hossler", "country": "UNITED STATES", "abbr_name": "B.Hossler"}, {"id": "6cad8490-72de-4df2-9d6a-ee1be88df338", "first_name": "Mackenzie", "last_name": "Hughes", "country": "CANADA", "abbr_name": "M.Hughes"}, {"id": "0c6211a3-ded4-49cf-a63c-190fbbff0ea0", "first_name": "John", "last_name": "Huh", "country": "UNITED STATES", "abbr_name": "J.Huh"}, {"id": "ac1db384-8cb4-4223-bc46-60f4ed963645", "first_name": "Sungjae", "last_name": "Im", "country": "SOUTH KOREA", "abbr_name": "S.Im"}, {"id": "8be4c74e-29f3-402f-b749-2109797b9794", "first_name": "Matt", "last_name": "Jones", "country": "AUSTRALIA", "abbr_name": "M.Jones"}, {"id": "c02f6992-be12-4b5a-9440-a083251610a3", "first_name": "Sung", "last_name": "Kang", "country": "SOUTH KOREA", "abbr_name": "S.Kang"}, {"id": "3442d4dd-ecfa-43aa-9a01-7525e6f4952c", "first_name": "Patton", "last_name": "Kizzire", "country": "UNITED STATES", "abbr_name": "P.Kizzire"}, {"id": "0e1589f1-3921-4b6b-9003-29a4f38415bb", "first_name": "Russell", "last_name": "Knox", "country": "SCOTLAND", "abbr_name": "R.Knox"}, {"id": "a6e8282b-2a5d-44fb-b28a-4e5c27770aaf", "first_name": "Satoshi", "last_name": "Kodaira", "country": "JAPAN", "abbr_name": "S.Kodaira"}, {"id": "2a94c1a7-66a0-4917-8a05-6873ed4932fd", "first_name": "Jason", "last_name": "Kokrak", "country": "UNITED STATES", "abbr_name": "J.Kokrak"}, {"id": "578615f4-d4a1-45d3-83cf-9a106dbc95a6", "first_name": "Anirban", "last_name": "Lahiri", "country": "INDIA", "abbr_name": "A.Lahiri"}, {"id": "45a571da-a1e4-4d48-9f88-47bb5185f0d0", "first_name": "Martin", "last_name": "Laird", "country": "SCOTLAND", "abbr_name": "M.Laird"}, {"id": "89245f90-70cb-4177-943d-d8536b85e486", "first_name": "Hank", "last_name": "Lebioda", "country": "UNITED STATES", "abbr_name": "H.Lebioda"}, {"id": "f8486bd4-0fc5-4117-b69b-7151f74f6b16", "first_name": "Nelson", "last_name": "Ledesma", "country": "ARGENTINA", "abbr_name": "N.Ledesma"}, {"id": "a4978416-8ed7-4884-ac5f-2bc941b0801d", "first_name": "Danny", "last_name": "Lee", "country": "NEW ZEALAND", "abbr_name": "D.Lee"}, {"id": "ad2405f8-2e7c-4c32-abfc-ad0a7e703244", "first_name": "Kyoung-Hoon", "last_name": "Lee", "country": "SOUTH KOREA", "abbr_name": "K.Lee"}, {"id": "6873b37f-d2ed-46e2-8d4a-8b30ba67311c", "first_name": "Marc", "last_name": "Leishman", "country": "AUSTRALIA", "abbr_name": "M.Leishman"}, {"id": "10fd713c-98d6-4add-bd83-78a8d74a2c24", "first_name": "KK", "last_name": "Limbhasut", "country": "THAILAND", "abbr_name": "K.Limbhasut"}, {"id": "59e38135-5887-43e5-b6ab-25cbfedcd6e5", "first_name": "Luke", "last_name": "List", "country": "UNITED STATES", "abbr_name": "L.List"}, {"id": "6fc571b9-d66d-424a-bcde-71ab62e4a35e", "first_name": "Jamie", "last_name": "Lovemark", "country": "UNITED STATES", "abbr_name": "J.Lovemark"}, {"id": "411767e2-5dee-4ac7-9646-9660d26b4bae", "first_name": "Hunter", "last_name": "Mahan", "country": "UNITED STATES", "abbr_name": "H.Mahan"}, {"id": "5ccb172d-5bbd-4302-a0ad-43ad9ffff64b", "first_name": "Peter", "last_name": "Malnati", "country": "UNITED STATES", "abbr_name": "P.Malnati"}, {"id": "495ca7e9-452f-405b-b515-efaf00ff41e0", "first_name": "Patrick", "last_name": "Martin", "country": "UNITED STATES", "abbr_name": "P.Martin"}, {"id": "59d30dae-b011-4a24-a7c1-285c4e4caf46", "first_name": "Ben", "last_name": "Martin", "country": "UNITED STATES", "abbr_name": "B.Martin"}, {"id": "d45bcf4a-5803-4b0b-ab6c-6427a76cecf7", "first_name": "Hideki", "last_name": "Matsuyama", "country": "JAPAN", "abbr_name": "H.Matsuyama"}, {"id": "6787bd96-6bf0-4297-b819-85025f81a3a9", "first_name": "Denny", "last_name": "McCarthy", "country": "UNITED STATES", "abbr_name": "D.McCarthy"}, {"id": "71ee7608-0254-4410-b2a4-e9926587d587", "first_name": "Tyler", "last_name": "McCumber", "country": "UNITED STATES", "abbr_name": "T.McCumber"}, {"id": "da226913-b804-48de-adbf-96e956eb75ac", "first_name": "Rory", "last_name": "McIlroy", "country": "NORTHERN IRELAND", "abbr_name": "R.McIlroy"}, {"id": "37221a6c-c8c4-4eaa-beba-715f6e781962", "first_name": "Maverick", "last_name": "McNealy", "country": "UNITED STATES", "abbr_name": "M.McNealy"}, {"id": "3f423647-083c-4da9-8ee6-344df4af116f", "first_name": "Phil", "last_name": "Mickelson", "country": "UNITED STATES", "abbr_name": "P.Mickelson"}, {"id": "21cad9ff-689e-4a99-b3a9-91f66cec3f01", "first_name": "Keith", "last_name": "Mitchell", "country": "UNITED STATES", "abbr_name": "K.Mitchell"}, {"id": "37f07f5b-f185-42d1-ad9a-f665df493554", "first_name": "Francesco", "last_name": "Molinari", "country": "ITALY", "abbr_name": "F.Molinari"}, {"id": "f0ff1391-fc29-41bf-b46a-cd5ef9f63ad9", "first_name": "Collin", "last_name": "Morikawa", "country": "UNITED STATES", "abbr_name": "C.Morikawa"}, {"id": "eadf7368-e673-4775-92ee-62c9b54a2f3e", "first_name": "Trey", "last_name": "Mullinax", "country": "UNITED STATES", "abbr_name": "T.Mullinax"}, {"id": "47fb8832-bf6c-4c00-a944-160b6f42fae6", "first_name": "Sebastian", "last_name": "Munoz", "country": "COLOMBIA", "abbr_name": "S.Munoz"}, {"id": "7edd8344-4f0b-4ea0-beb2-cdb5c093890f", "first_name": "Grayson", "last_name": "Murray", "country": "UNITED STATES", "abbr_name": "G.Murray"}, {"id": "495479d6-cc8c-4a33-bce1-19d76de4448b", "first_name": "Matthew", "last_name": "NeSmith", "country": "UNITED STATES", "abbr_name": "M.NeSmith"}, {"id": "4249bf6e-9723-4a4a-9ddd-515022618de9", "first_name": "Joaquin", "last_name": "Niemann", "country": "CHILE", "abbr_name": "J.Niemann"}, {"id": "7d470d98-95a1-42a5-b5eb-39bd2259ac5f", "first_name": "Seung-Yul", "last_name": "Noh", "country": "SOUTH KOREA", "abbr_name": "S.Noh"}, {"id": "cb867fe8-660d-43de-9486-c80cc0837190", "first_name": "Henrik", "last_name": "Norlander", "country": "SWEDEN", "abbr_name": "H.Norlander"}, {"id": "17d138ad-3c4a-4a0a-a0ea-a4398035a186", "first_name": "Eddie", "last_name": "Olson", "country": "UNITED STATES", "abbr_name": "E.Olson"}, {"id": "0f455b60-77bb-45f6-849d-9b4a711cf4ab", "first_name": "Rob", "last_name": "Oppenheim", "country": "UNITED STATES", "abbr_name": "R.Oppenheim"}, {"id": "b3bd6986-a84b-4f83-aee6-65a49c4ca502", "first_name": "Carlos", "last_name": "Ortiz", "country": "MEXICO", "abbr_name": "C.Ortiz"}, {"id": "16f48e54-5d7e-45b8-9734-00dce86cf4e2", "first_name": "Ryan", "last_name": "Palmer", "country": "UNITED STATES", "abbr_name": "R.Palmer"}, {"id": "49fb93d3-5dbe-448f-a0cb-d851087f2019", "first_name": "C.T.", "last_name": "Pan", "country": "CHINESE TAIPEI", "abbr_name": "C.Pan"}, {"id": "752f287c-7ed1-4af9-9686-ede38f07fedd", "first_name": "Cameron", "last_name": "Percy", "country": "AUSTRALIA", "abbr_name": "C.Percy"}, {"id": "827eafe9-e092-4020-bc94-634b031900ed", "first_name": "Pat", "last_name": "Perez", "country": "UNITED STATES", "abbr_name": "P.Perez"}, {"id": "03bdd912-c363-4517-99b5-7a1ec757ebe5", "first_name": "Ted", "last_name": "Potter Jr.", "country": "UNITED STATES", "abbr_name": "T.Potter Jr."}, {"id": "7b52b9be-a490-4569-9bbc-57db5f232dcb", "first_name": "Jon", "last_name": "Rahm", "country": "SPAIN", "abbr_name": "J.Rahm"}, {"id": "05d808bc-da95-4d5f-ab1c-d02302959f81", "first_name": "Doc", "last_name": "Redman", "country": "UNITED STATES", "abbr_name": "D.Redman"}, {"id": "12195ed9-3fcd-486a-86b4-1ec726d201cd", "first_name": "Patrick", "last_name": "Reed", "country": "UNITED STATES", "abbr_name": "P.Reed"}, {"id": "261a8e12-ab08-4fd3-a5db-c61e6ceeadaf", "first_name": "Wes", "last_name": "Roach", "country": "UNITED STATES", "abbr_name": "W.Roach"}, {"id": "3888a78e-b24a-4005-8915-2f03fccf3107", "first_name": "Patrick", "last_name": "Rodgers", "country": "UNITED STATES", "abbr_name": "P.Rodgers"}, {"id": "c11235f6-0f62-4afb-93e7-952dc0554649", "first_name": "Justin", "last_name": "Rose", "country": "ENGLAND", "abbr_name": "J.Rose"}, {"id": "229faa9c-fc01-46bb-a8cb-f6b0310a8cef", "first_name": "Sam", "last_name": "Ryder", "country": "UNITED STATES", "abbr_name": "S.Ryder"}, {"id": "2b2a6adc-ff1d-4bc2-9dbd-70781d6fbe89", "first_name": "Rory", "last_name": "Sabbatini", "country": "SLOVAKIA", "abbr_name": "R.Sabbatini"}, {"id": "31882cce-ff39-4b49-8527-8575c8efaa49", "first_name": "Isaiah", "last_name": "Salinda", "country": "UNITED STATES", "abbr_name": "I.Salinda"}, {"id": "26dc0bda-b9a8-4303-9c1c-ddecda3817d2", "first_name": "Xander", "last_name": "Schauffele", "country": "UNITED STATES", "abbr_name": "X.Schauffele"}, {"id": "6db3e736-d86d-4181-aa3b-651b8c1bfdc1", "first_name": "Scottie", "last_name": "Scheffler", "country": "UNITED STATES", "abbr_name": "S.Scheffler"}, {"id": "e2f0f097-2411-4255-8d86-5ea58682a72e", "first_name": "Chase", "last_name": "Seiffert", "country": "UNITED STATES", "abbr_name": "C.Seiffert"}, {"id": "1eaf61ab-e7e2-4d75-a93a-d9ff1335126e", "first_name": "John", "last_name": "Senden", "country": "AUSTRALIA", "abbr_name": "J.Senden"}, {"id": "2dd3fb39-dd0d-41be-b275-a916e1165389", "first_name": "Robby", "last_name": "Shelton", "country": "UNITED STATES", "abbr_name": "R.Shelton"}, {"id": "a1cc8510-a993-4f52-a79c-ada07decd200", "first_name": "Roger", "last_name": "Sloan", "country": "CANADA", "abbr_name": "R.Sloan"}, {"id": "aee6ead9-10e0-445b-aa13-d037cc1dd861", "first_name": "Cameron", "last_name": "Smith", "country": "AUSTRALIA", "abbr_name": "C.Smith"}, {"id": "d58435c9-e14c-404b-b13b-3de15f6c92be", "first_name": "Brandt", "last_name": "Snedeker", "country": "UNITED STATES", "abbr_name": "B.Snedeker"}, {"id": "7fdc75ca-2c33-49b8-8738-a8ea06fb51ed", "first_name": "J.J.", "last_name": "Spaun", "country": "UNITED STATES", "abbr_name": "J.Spaun"}, {"id": "3e4963cb-6e80-4393-85cf-2aecec453c4a", "first_name": "Jordan", "last_name": "Spieth", "country": "UNITED STATES", "abbr_name": "J.Spieth"}, {"id": "450bddc0-b8de-46a5-ba9d-7a8b2277d09c", "first_name": "Kevin", "last_name": "Stadler", "country": "UNITED STATES", "abbr_name": "K.Stadler"}, {"id": "d28839e8-d9f0-483f-9932-227775cb78cf", "first_name": "Scott", "last_name": "Stallings", "country": "UNITED STATES", "abbr_name": "S.Stallings"}, {"id": "c44c8311-3669-4bc0-b25e-a7bbf5e53cf8", "first_name": "Kyle", "last_name": "Stanley", "country": "UNITED STATES", "abbr_name": "K.Stanley"}, {"id": "5003f675-818b-410a-9f2e-1a860d152900", "first_name": "Brendan", "last_name": "Steele", "country": "UNITED STATES", "abbr_name": "B.Steele"}, {"id": "502087cf-2c40-4e1d-9649-4f4e6d7d7778", "first_name": "Sepp", "last_name": "Straka", "country": "AUSTRIA", "abbr_name": "S.Straka"}, {"id": "16d8796c-7927-4d1b-b926-b2d906dbc64e", "first_name": "Robert", "last_name": "Streb", "country": "UNITED STATES", "abbr_name": "R.Streb"}, {"id": "4f8a4f4d-8359-4187-b506-3da3ad5b05fb", "first_name": "Kevin", "last_name": "Streelman", "country": "UNITED STATES", "abbr_name": "K.Streelman"}, {"id": "1e4bf43f-dda6-4d88-87c5-d3a229c99a44", "first_name": "Steve", "last_name": "Stricker", "country": "UNITED STATES", "abbr_name": "S.Stricker"}, {"id": "856463cb-4289-4cc0-9f55-e97042a21cd8", "first_name": "Chris", "last_name": "Stroud", "country": "UNITED STATES", "abbr_name": "C.Stroud"}, {"id": "d640be3c-90b7-422a-8599-022e414f8541", "first_name": "Zack", "last_name": "Sucher", "country": "UNITED STATES", "abbr_name": "Z.Sucher"}, {"id": "669d9c4b-7169-484d-99bb-0f86e1e2a3db", "first_name": "Justin", "last_name": "Suh", "country": "UNITED STATES", "abbr_name": "J.Suh"}, {"id": "9cf73afd-cf7b-4c9e-9dfc-14ffc277c29e", "first_name": "Ben", "last_name": "Taylor", "country": "ENGLAND", "abbr_name": "B.Taylor"}, {"id": "91435c6c-5800-4cd5-afc1-8d2ece36215e", "first_name": "Josh", "last_name": "Teater", "country": "UNITED STATES", "abbr_name": "J.Teater"}, {"id": "6ad1215a-824f-43e4-9bbe-169a5df02cc2", "first_name": "Michael", "last_name": "Thompson", "country": "UNITED STATES", "abbr_name": "M.Thompson"}, {"id": "cb55280e-419f-4347-9ea1-f37637c5669c", "first_name": "D.J.", "last_name": "Trahan", "country": "UNITED STATES", "abbr_name": "D.Trahan"}, {"id": "313d2569-5a3d-4fad-a6c9-b7100751a491", "first_name": "Martin", "last_name": "Trainer", "country": "UNITED STATES", "abbr_name": "M.Trainer"}, {"id": "1fff624d-360d-4733-bbc5-ca444bc44243", "first_name": "Cameron", "last_name": "Tringale", "country": "UNITED STATES", "abbr_name": "C.Tringale"}, {"id": "652e84b2-3511-4673-b9cc-2705764c67f6", "first_name": "Kevin", "last_name": "Tway", "country": "UNITED STATES", "abbr_name": "K.Tway"}, {"id": "3f82c91a-47f0-4551-8500-04784e940cde", "first_name": "Peter", "last_name": "Uihlein", "country": "UNITED STATES", "abbr_name": "P.Uihlein"}, {"id": "19564b63-f9c8-4263-a689-3135b7755631", "first_name": "Harold", "last_name": "Varner III", "country": "UNITED STATES", "abbr_name": "H.Varner III"}, {"id": "4c25a86b-b1ff-46b4-bc95-ac61dda7bb55", "first_name": "Jhonattan", "last_name": "Vegas", "country": "VENEZUELA", "abbr_name": "J.Vegas"}, {"id": "a9053c60-3cc0-48cb-bcf2-4848963f352d", "first_name": "Kristoffer", "last_name": "Ventura", "country": "NORWAY", "abbr_name": "K.Ventura"}, {"id": "2db60f6e-7b0a-4daf-97d9-01a057f44f1d", "first_name": "Jimmy", "last_name": "Walker", "country": "UNITED STATES", "abbr_name": "J.Walker"}, {"id": "8ed30358-ddd0-4704-8b72-3e711b73a73e", "first_name": "Nick", "last_name": "Watney", "country": "UNITED STATES", "abbr_name": "N.Watney"}, {"id": "414bf151-7adc-4857-801d-ef2d7f84953e", "first_name": "Bubba", "last_name": "Watson", "country": "UNITED STATES", "abbr_name": "B.Watson"}, {"id": "325e7b91-03b8-4013-bd77-f476303e7d94", "first_name": "Richy", "last_name": "Werenski", "country": "UNITED STATES", "abbr_name": "R.Werenski"}, {"id": "c6c566d2-bdbf-484d-a581-3036ad95ee57", "first_name": "Vincent", "last_name": "Whaley", "country": "USA", "abbr_name": "V.Whaley"}, {"id": "e6857a2c-3e49-4b74-990d-93e7ea501b63", "first_name": "Tim", "last_name": "Wilkinson", "country": "NEW ZEALAND", "abbr_name": "T.Wilkinson"}, {"id": "e202181a-c36f-4c16-81a7-dc1c97c1d88f", "first_name": "Matthew", "last_name": "Wolff", "country": "UNITED STATES", "abbr_name": "M.Wolff"}, {"id": "2d568087-700f-44a2-8390-47aa7bafc770", "first_name": "Gary", "last_name": "Woodland", "country": "UNITED STATES", "abbr_name": "G.Woodland"}, {"id": "d74e6369-dcb4-4225-8152-90d3f19d2517", "first_name": "Tiger", "last_name": "Woods", "country": "UNITED STATES", "abbr_name": "T.Woods"}, {"id": "e8448c58-d9af-4b4a-8238-4275cf7ab383", "first_name": "Brandon", "last_name": "Wu", "country": "UNITED STATES", "abbr_name": "B.Wu"}, {"id": "084086c6-3fa4-45e6-be4b-ea9467da8197", "first_name": "Xinjun", "last_name": "Zhang", "country": "CHINA", "abbr_name": "X.Zhang"}]}